wkhtmltopdf_wrapper-0.3.3.dist-info/DESCRIPTION.rst
wkhtmltopdf_wrapper-0.3.3.dist-info/METADATA
wkhtmltopdf_wrapper-0.3.3.dist-info/metadata.json
wkhtmltopdf_wrapper-0.3.3.dist-info/RECORD
wkhtmltopdf_wrapper-0.3.3.dist-info/top_level.txt
wkhtmltopdf_wrapper-0.3.3.dist-info/WHEEL
wkhtmltopdfwrapper/__init__.py
