Metadata-Version: 2.0
Name: wkhtmltopdf-wrapper
Version: 0.3.3
Summary: A Simpler python wrapper for wkhtmltopdf, inspired by Qoda's python-wkhtmltopdf
Home-page: http://github.com/aguegu/wkhtmltopdf-wrapper
Author: aGuegu
Author-email: weihong.guan@gmail.com
License: BSD
Keywords: wkhtmltopdf pdf
Platform: UNKNOWN
Classifier: Programming Language :: Python
Classifier: License :: OSI Approved :: BSD License
Classifier: Development Status :: 4 - Beta
Classifier: Operating System :: OS Independent
Classifier: Intended Audience :: Developers
Classifier: Topic :: Internet :: WWW/HTTP :: Dynamic Content
